secretum_sphinx_theme/__init__.py
secretum_sphinx_theme/dark_mode_loader.py
secretum_sphinx_theme/static/dark_mode_css/dark.css
secretum_sphinx_theme/static/dark_mode_css/general.css
secretum_sphinx_theme/static/dark_mode_js/default_dark.js
secretum_sphinx_theme/static/dark_mode_js/default_light.js
secretum_sphinx_theme/static/dark_mode_js/theme_switcher.js
secretum_sphinx_theme-2022.2.dist-info/LICENSE
secretum_sphinx_theme-2022.2.dist-info/METADATA
secretum_sphinx_theme-2022.2.dist-info/WHEEL
secretum_sphinx_theme-2022.2.dist-info/top_level.txt
secretum_sphinx_theme-2022.2.dist-info/RECORD
