Metadata-Version: 2.1
Name: secretum-sphinx-theme
Version: 2022.2
Summary: Dark mode for the Sphinx Read the Docs theme.
Home-page: https://github.com/scalabli/secretum_sphinx_theme
Author: Gerrishon Sirere
License: MIT
Download-URL: https://github.com/scalabli/secretum_sphinx_theme/archive/v2022.2.tar.gz
Platform: UNKNOWN
Classifier: Development Status :: 5 - Production/Stable
Classifier: Natural Language :: English
Classifier: Programming Language :: Python :: 3.5
Classifier: Programming Language :: Python :: 3.6
Classifier: Programming Language :: Python :: 3.7
Classifier: Programming Language :: Python :: 3.8
Classifier: Programming Language :: Python :: 3.9
Classifier: Programming Language :: Python :: 3.10
Classifier: License :: OSI Approved :: MIT License
Classifier: Operating System :: OS Independent
Requires-Python: >=3.6
License-File: LICENSE
Requires-Dist: sphinx-rtd-theme
